mcp_server_hw_test/__init__.py
mcp_server_hw_test/server.py
mcp_server_hw_test-0.1.3.dist-info/WHEEL
mcp_server_hw_test-0.1.3.dist-info/entry_points.txt
mcp_server_hw_test-0.1.3.dist-info/METADATA
mcp_server_hw_test-0.1.3.dist-info/RECORD
