Metadata-Version: 2.3
Name: mcp-server-hw-test
Version: 0.1.3
Summary: A MCP server project
Author: yaojiebin
Author-email: yaojiebin <1594504390@qq.com>
Requires-Dist: mcp>=1.15.0
Requires-Python: >=3.11
